Metadata-Version: 2.4
Name: tiago-image_processing
Version: 0.0.1
Summary: Image processing package using Skimage
Home-page: https://github.com/tiagoosr
Author: tiago-image_processing
Requires-Python: >=3.8
Requires-Dist: matplotlib
Requires-Dist: numpy
Requires-Dist: scikit-image>=0.16.1
Dynamic: author
Dynamic: description
Dynamic: description-content-type
Dynamic: home-page
Dynamic: requires-dist
Dynamic: requires-python
Dynamic: summary
